README.md
pyproject.toml
setup.cfg
setup.py
jaepeto/__init__.py
jaepeto.egg-info/PKG-INFO
jaepeto.egg-info/SOURCES.txt
jaepeto.egg-info/dependency_links.txt
jaepeto.egg-info/entry_points.txt
jaepeto.egg-info/requires.txt
jaepeto.egg-info/top_level.txt
jaepeto/docs/__init__.py
jaepeto/docs/changelog.py
jaepeto/docs/technical_docs.py
jaepeto/integration/__init__.py
jaepeto/patterns/__init__.py
jaepeto/patterns/interactions.py
jaepeto/patterns/packages.py
jaepeto/patterns/tools.py
jaepeto/structure/__init__.py
jaepeto/structure/classes.py
jaepeto/structure/entrypoint.py
jaepeto/structure/hello_world.py
jaepeto/summaries/__init__.py
jaepeto/summaries/functions.py
jaepeto/utils/__init__.py
jaepeto/utils/config.py
jaepeto/utils/git.py
jaepeto/utils/parse_python.py
jaepeto/utils/requests.py