Metadata-Version: 2.1
Name: jaepeto
Version: 0.5.0
Summary: API interface for generating documentation for Python projects
Home-page: UNKNOWN
Author: Jaepeto
License: UNKNOWN
Platform: UNKNOWN
